README.md
setup.py
fet/__init__.py
fet/basic.py
fet/common.py
fet/explorer.py
fet/pstats.py
nemea_fet.egg-info/PKG-INFO
nemea_fet.egg-info/SOURCES.txt
nemea_fet.egg-info/dependency_links.txt
nemea_fet.egg-info/requires.txt
nemea_fet.egg-info/top_level.txt