Metadata-Version: 2.1
Name: nemea-fet
Version: 0.1.2
Summary: Nemea Feature Exploration Toolkit
Home-page: https://github.com/danieluhricek/nemea-fet
Author: Daniel Uhříček
Author-email: daniel.uhricek@gypri.cz
License: UNKNOWN
Platform: UNKNOWN
